biobb_haddock/__init__.py
biobb_haddock/py.typed
biobb_haddock/haddock/__init__.py
biobb_haddock/haddock/capri_eval.py
biobb_haddock/haddock/clust_fcc.py
biobb_haddock/haddock/common.py
biobb_haddock/haddock/contact_map.py
biobb_haddock/haddock/em_ref.py
biobb_haddock/haddock/flex_ref.py
biobb_haddock/haddock/haddock3_config.py
biobb_haddock/haddock/haddock3_extend.py
biobb_haddock/haddock/haddock3_run.py
biobb_haddock/haddock/rigid_body.py
biobb_haddock/haddock/sele_top.py
biobb_haddock/haddock/sele_top_clusts.py
biobb_haddock/haddock/topology.py
biobb_haddock/haddock_restraints/__init__.py
biobb_haddock/haddock_restraints/haddock3_accessibility.py
biobb_haddock/haddock_restraints/haddock3_actpass_to_ambig.py
biobb_haddock/haddock_restraints/haddock3_passive_from_active.py
biobb_haddock/haddock_restraints/haddock3_restrain_bodies.py
biobb_haddock/test/__init__.py
biobb_haddock-5.2.0.dist-info/licenses/LICENSE
biobb_haddock-5.2.0.dist-info/METADATA
biobb_haddock-5.2.0.dist-info/WHEEL
biobb_haddock-5.2.0.dist-info/entry_points.txt
biobb_haddock-5.2.0.dist-info/top_level.txt
biobb_haddock-5.2.0.dist-info/RECORD
