Metadata-Version: 2.4
Name: biobb_haddock
Version: 5.2.0
Summary: biobb_haddock is the Biobb module collection to compute information-driven flexible protein-protein docking.
Home-page: https://github.com/bioexcel/biobb_haddock
Author: Biobb developers
Author-email: ruben.chaves@irbbarcelona.org
Project-URL: Documentation, http://biobb_haddock.readthedocs.io/en/latest/
Project-URL: Bioexcel, https://bioexcel.eu/
Keywords: Bioinformatics Workflows BioExcel Compatibility
Classifier: Development Status :: 5 - Production/Stable
Classifier: Programming Language :: Python :: 3.10
Classifier: License :: OSI Approved :: Apache Software License
Classifier: Operating System :: MacOS :: MacOS X
Classifier: Operating System :: POSIX
Classifier: Operating System :: Unix
Requires-Python: >=3.10
License-File: LICENSE
Requires-Dist: biobb_common==5.2.0
Dynamic: author
Dynamic: author-email
Dynamic: classifier
Dynamic: description
Dynamic: description-content-type
Dynamic: home-page
Dynamic: keywords
Dynamic: license-file
Dynamic: project-url
Dynamic: requires-dist
Dynamic: requires-python
Dynamic: summary
